machwave/common/__init__.py
machwave/common/arrays.py
machwave/common/decorators.py
machwave/common/generic.py
machwave/core/__init__.py
machwave/core/conversions.py
machwave/core/des.py
machwave/core/flow/__init__.py
machwave/core/flow/incompressible.py
machwave/core/flow/isentropic.py
machwave/core/losses.py
machwave/core/mathematics/__init__.py
machwave/core/mathematics/geometric.py
machwave/core/mathematics/rk4.py
machwave/core/structural/__init__.py
machwave/core/structural/bolted_joints.py
machwave/core/structural/pressure_vessels.py
machwave/io/__init__.py
machwave/io/eng.py
machwave/models/__init__.py
machwave/models/atmosphere/__init__.py
machwave/models/atmosphere/atm_1976.py
machwave/models/atmosphere/base.py
machwave/models/materials/__init__.py
machwave/models/materials/base.py
machwave/models/materials/metals.py
machwave/models/materials/polymers.py
machwave/models/propulsion/__init__.py
machwave/models/propulsion/feed_systems/__init__.py
machwave/models/propulsion/feed_systems/base.py
machwave/models/propulsion/feed_systems/pressure_fed.py
machwave/models/propulsion/feed_systems/tanks/__init__.py
machwave/models/propulsion/feed_systems/tanks/base.py
machwave/models/propulsion/grain/__init__.py
machwave/models/propulsion/grain/base.py
machwave/models/propulsion/grain/fmm/_2d.py
machwave/models/propulsion/grain/fmm/_3d.py
machwave/models/propulsion/grain/fmm/__init__.py
machwave/models/propulsion/grain/fmm/base.py
machwave/models/propulsion/grain/fmm/services.py
machwave/models/propulsion/grain/fmm/stl.py
machwave/models/propulsion/grain/geometries/__init__.py
machwave/models/propulsion/grain/geometries/bates.py
machwave/models/propulsion/grain/geometries/conical.py
machwave/models/propulsion/grain/geometries/d_grain.py
machwave/models/propulsion/grain/geometries/multi_port.py
machwave/models/propulsion/grain/geometries/rod_and_tube.py
machwave/models/propulsion/grain/geometries/star.py
machwave/models/propulsion/grain/geometries/wagon_wheel.py
machwave-1.0.0.dist-info/METADATA
machwave-1.0.0.dist-info/WHEEL
machwave-1.0.0.dist-info/RECORD
