Metadata-Version: 2.3
Name: machwave
Version: 1.0.0
Summary: Rocket simulator
License: GNU GENERAL PUBLIC LICENSE
Keywords: python,rocket,srm,engine,propulsion
Author: Felipe Bogaerts de Mattos
Author-email: me@felipebm.com
Requires-Python: >=3.11,<=3.14
Classifier: Programming Language :: Python :: 3
Classifier: Operating System :: Unix
Classifier: Operating System :: MacOS :: MacOS X
Classifier: Operating System :: Microsoft :: Windows
Requires-Dist: coolprop (>=6.7.0,<7.0.0)
Requires-Dist: fluids (>=1.1.0,<2.0.0)
Requires-Dist: matplotlib (>=3.10.0,<4.0.0)
Requires-Dist: numpy (>=2.0.0,<3.0.0)
Requires-Dist: pandas (>=2.2.3,<3.0.0)
Requires-Dist: plotly (>=6.0.0,<7.0.0)
Requires-Dist: rocketcea (>=1.2.1,<2.0.0)
Requires-Dist: scikit-fmm (==2025.6.23)
Requires-Dist: scikit-image (>=0.25.2,<0.26.0)
Requires-Dist: scipy (>=1.15.2,<2.0.0)
Requires-Dist: trimesh (>=4.6.4,<5.0.0)
Project-URL: Homepage, https://github.com/felipebogaertsm/machwave
